FAIRSave/__init__.py
FAIRSave/configuration.py
FAIRSave/eln_manager.py
FAIRSave/kadi_download.py
FAIRSave/kadi_identifier.py
FAIRSave/kadi_instances.py
FAIRSave/kadi_json_writer.py
FAIRSave/kadi_record.py
FAIRSave/kadi_search.py
FAIRSave/kadi_template.py
FAIRSave/tools/__init__.py
FAIRSave/tools/comparison.py
FAIRSave/tools/difference.py
FAIRSave/tools/json_reader.py
FAIRSave/tools/key.py
FAIRSave/tools/metadata.py
FAIRSave/tools/surftheowl_json.py
FAIRSave/tools/validation.py
FAIRSave-0.0.6.14.dist-info/LICENSE
FAIRSave-0.0.6.14.dist-info/METADATA
FAIRSave-0.0.6.14.dist-info/WHEEL
FAIRSave-0.0.6.14.dist-info/top_level.txt
FAIRSave-0.0.6.14.dist-info/RECORD
