Metadata-Version: 2.1
Name: FAIRSave
Version: 0.0.6.14
Summary: Package to run the FAIR-Save toolbox
Author: Malte Flachmann, Floriane Bresser, Ilia Bagov (Karlsruhe Institute of Technology)
Author-email: malte.flachmann@kit.edu
License: Apache-2.0
Project-URL: GitLab, https://gitlab.com/linked-tribological-data/fair-save/FAIR-Save_Utilities
Project-URL: Changelog, https://gitlab.com/linked-tribological-data/fair-save/FAIR-Save-Utilities/-/blob/main/Changelog.md
Keywords: Kadi4Mat,FAIR
Requires-Python: >=3.10
License-File: LICENSE
Requires-Dist: kadi-apy >=0.25.0
Requires-Dist: xmltodict >=0.13.0
Requires-Dist: nested-lookup >=0.2.25
